{"name":"Editing a DvSum View","id":"edit-view;editing-a-dvsum-view","testSteps":[{"number":1,"description":"Given User is on Column Dictionary Page on DvSum App","duration":0,"startTime":"2020-11-30T18:51:24.672773900+05:00[Asia/Karachi]","result":"SUCCESS","precondition":false,"level":0},{"number":2,"description":"When User edits a view","duration":15,"startTime":"2020-11-30T18:51:24.672773900+05:00[Asia/Karachi]","result":"SUCCESS","precondition":false,"level":0},{"number":3,"description":"Then View should be updated with edited details","duration":0,"startTime":"2020-11-30T18:51:24.688400500+05:00[Asia/Karachi]","result":"SUCCESS","precondition":false,"level":0}],"userStory":{"id":"edit-view","storyName":"Edit View","path":"file:///C:/Users/Emumba/IdeaProjects/serenityCucumberDemo/serenitydemo/src/test/resources/features/dvsum/edit_view.feature","type":"feature"},"featureTag":{"name":"Dvsum/Edit View","type":"feature","displayName":"Dvsum/Edit View"},"title":"Editing a DvSum View","description":"","tags":[{"name":"Dvsum/Edit View","type":"feature","displayName":"Edit View"},{"name":"Dvsum","type":"capability","displayName":"Dvsum"}],"startTime":"2020-11-30T18:51:24.438391600+05:00[Asia/Karachi]","duration":250,"projectKey":"","isManualTestingUpToDate":false,"manual":false,"testSource":"Cucumber","actors":[{"name":"Checo","can":["browse the web"]}],"result":"SUCCESS"}